ndx_hed/spec/ndx-hed.extensions.yaml
ndx_hed/spec/ndx-hed.namespace.yaml
ndx_hed/__init__.py
ndx_hed/hed_lab_metadata.py
ndx_hed/hed_tags.py
ndx_hed/utils/__init__.py
ndx_hed/utils/bids2nwb.py
ndx_hed/utils/hed_nwb_validator.py
ndx_hed-0.2.0.dist-info/METADATA
ndx_hed-0.2.0.dist-info/WHEEL
ndx_hed-0.2.0.dist-info/licenses/LICENSE.txt
ndx_hed-0.2.0.dist-info/RECORD
