Metadata-Version: 2.4
Name: ndx-hed
Version: 0.2.0
Summary: NWB extension for HED data
Project-URL: Homepage, https://github.com/hed-standard/ndx-hed
Project-URL: Documentation, https://www.hed-resources.org/en/latest/HedAnnotationInNWB.html
Project-URL: Bug Tracker, https://github.com/hed-standard/ndx-hed/issues
Project-URL: Discussions, https://github.com/hed-standard/ndx-hed/discussions
Project-URL: Changelog, https://github.com/hed-standard/ndx-hed/CHANGELOG.md
Author-email: Kay Robbins <kay.robbins@utsa.edu>, Ryan Ly <rly@lbl.gov>, Oliver Ruebel <oruebel@lbl.gov>, Ian Callanan <ianrcallanan@gmail.com>
License: BSD-3
License-File: LICENSE.txt
Keywords: NWB,NeurodataWithoutBorders,ndx-extension,nwb-extension
Classifier: Development Status :: 5 - Production/Stable
Classifier: Intended Audience :: Developers
Classifier: Intended Audience :: Science/Research
Classifier: License :: OSI Approved :: BSD License
Classifier: Programming Language :: Python
Classifier: Programming Language :: Python :: 3.10
Classifier: Programming Language :: Python :: 3.11
Classifier: Programming Language :: Python :: 3.12
Classifier: Programming Language :: Python :: 3.13
Classifier: Programming Language :: Python :: 3.14
Requires-Python: >=3.10
Requires-Dist: hdmf>=3.14.1
Requires-Dist: hedtools>=0.7.1
Requires-Dist: pynwb>=2.8.2
